iverilog_divi/control_divi.v
module control_divi (clk, rst, init, Z_A, Z_B, LD, SH, SUB, ADD_C, done);
    
input clk;
input rst;
input init;
input Z_A;
input Z_B;

output reg LD;
output reg SH;
output reg SUB;
output reg ADD_C;
output reg done;

parameter START      = 3'b000;
parameter CHECK      = 3'b001;
parameter SUBTRACT   = 3'b010;
parameter SHIFT      = 3'b011;
parameter CHECK_END  = 3'b100;
parameter END_STATE  = 3'b101;

reg [2:0] state;
reg [2:0] next_state;

always @(posedge clk or posedge rst)
begin
  if(rst)
    state <= START;
  else
    state <= next_state;
end

always @(*)
begin
  next_state = state;

    case(state)

        START:
        begin
            if(init)
                next_state = CHECK;
        end

        CHECK:
        begin
            if(Z_A)
                next_state = SUBTRACT;
            else
                next_state = SHIFT;
            end

        SUBTRACT:
        begin
            next_state = SHIFT;
        end

        SHIFT:
        begin
            next_state = CHECK_END;
        end

        CHECK_END:
        begin
            if(Z_B)
                next_state = END_STATE;
            else
                next_state = CHECK;
        end

        END_STATE:
        begin
            if(!init)
                next_state = START;
        end

        default:
            next_state = START;

    endcase
end

always @(*)
begin

    LD    = 0;
    SH    = 0;
    SUB   = 0;
    ADD_C = 0;
    done  = 0;

    case(state)

        START:
        begin
            LD = 1;
        end

        CHECK:
        begin
        end

        SUBTRACT:
        begin
            SUB = 1;
        end

        SHIFT:
        begin
            SH    = 1;
            ADD_C = 1;
        end

        CHECK_END:
        begin
        end

        END_STATE:
        begin
            done = 1;
        end

    endcase
end

endmodule

iverilog_divi/control_divi_TB.v
`timescale 1ns/1ps
`define SIMULATION

module control_divi_TB;

reg clk;
reg rst;
reg init;
reg Z_A;
reg Z_B;

wire LD;
wire SH;
wire SUB;
wire ADD_C;
wire done;

control_divi utt(
    .clk(clk),
    .rst(rst),
    .init(init),
    .Z_A(Z_A),
    .Z_B(Z_B),
    .LD(LD),
    .SH(SH),
    .SUB(SUB),
    .ADD_C(ADD_C),
    .done(done)
);

parameter PERIOD = 20;

always #(PERIOD/2) clk = ~clk;

initial
begin
    clk  = 0;
    rst  = 1;
    init = 0;
    Z_A   = 0;
    Z_B   = 0;

    #30;
    rst = 0;

@(posedge clk);
init = 1;

@(posedge clk);
Z_A = 1;

@(posedge clk);

@(posedge clk);

Z_B = 0;

@(posedge clk);

Z_A = 0;

@(posedge clk);

@(posedge clk);

Z_B = 1;

@(posedge clk);

@(posedge clk);

init = 0;

@(posedge clk);

#50;
$finish;
end

 initial begin: TEST_CASE
 $dumpfile("control_divi_TB.vcd");
 $dumpvars(0, utt);
 #10000 $finish;
 end

endmodule

iverilog_divi/control_divi_TB.vcd
$date
	Thu Jun  4 14:14:27 2026
$end
$version
	Icarus Verilog
$end
$timescale
	1ps
$end
$scope module control_divi_TB $end
$scope module utt $end
$var wire 1 ! Z_A $end
$var wire 1 " Z_B $end
$var wire 1 # clk $end
$var wire 1 $ init $end
$var wire 1 % rst $end
$var parameter 3 & CHECK $end
$var parameter 3 ' CHECK_END $end
$var parameter 3 ( END_STATE $end
$var parameter 3 ) SHIFT $end
$var parameter 3 * START $end
$var parameter 3 + SUBTRACT $end
$var reg 1 , ADD_C $end
$var reg 1 - LD $end
$var reg 1 . SH $end
$var reg 1 / SUB $end
$var reg 1 0 done $end
$var reg 3 1 next_state [2:0] $end
$var reg 3 2 state [2:0] $end
$upscope $end
$upscope $end
$enddefinitions $end
$comment Show the parameter values. $end
$dumpall
b10 +
b0 *
b11 )
b101 (
b100 '
b1 &
$end
#0
$dumpvars
b0 2
b0 1
00
0/
0.
1-
0,
1%
0$
0#
0"
0!
$end
#10000
1#
#20000
0#
#30000
b1 1
1$
1#
0%
#40000
0#
#50000
0-
b1 2
b10 1
1!
1#
#60000
0#
#70000
1/
b11 1
b10 2
1#
#80000
0#
#90000
1,
1.
0/
b100 1
b11 2
1#
#100000
0#
#110000
0,
0.
b100 2
b1 1
0!
1#
#120000
0#
#130000
b11 1
b1 2
1#
#140000
0#
#150000
1,
1.
b11 2
b100 1
1"
1#
#160000
0#
#170000
0,
0.
b101 1
b100 2
1#
#180000
0#
#190000
10
b101 2
b0 1
0$
1#
#200000
0#
#210000
1-
00
b0 2
1#
